README
setup.py
django_sqlviews.egg-info/PKG-INFO
django_sqlviews.egg-info/SOURCES.txt
django_sqlviews.egg-info/dependency_links.txt
django_sqlviews.egg-info/top_level.txt
sqlviews/__init__.py
sqlviews/management/__init__.py
sqlviews/management/commands/__init__.py
sqlviews/management/commands/sqlviews.py