Metadata-Version: 1.1
Name: django-sqlviews
Version: 1.0
Summary: Management command for creating views of multi-table models
Home-page: http://github.com/seveas/django-sqlviews
Author: Dennis Kaarsemaker
Author-email: dennis@kaarsemaker.net
License: UNKNOWN
Platform: UNKNOWN
Classifier: Framework :: Django
Classifier: Intended Audience :: Developers
Classifier: Operating System :: OS Independent
Classifier: Topic :: Software Development
